kypo/aws_driver/__init__.py
kypo/aws_driver/aws_client.py
kypo/aws_driver/exceptions.py
kypo/aws_driver/templates/security-groups-template.j2
kypo/aws_driver/templates/terraform-deploy-template.j2
kypo/aws_driver/templates/terraform-provider-template.j2
kypo_aws_lib-0.3.7.dist-info/METADATA
kypo_aws_lib-0.3.7.dist-info/WHEEL
kypo_aws_lib-0.3.7.dist-info/RECORD
