Metadata-Version: 2.1
Name: kypo-aws-lib
Version: 0.3.7
Summary: KYPO AWS Driver Python lib
License: MIT
Author: Juraj Paluba
Author-email: 492988@mail.muni.cz
Requires-Python: >=3.10,<4.0
Classifier: License :: OSI Approved :: MIT License
Classifier: Programming Language :: Python :: 3
Classifier: Programming Language :: Python :: 3.10
Classifier: Programming Language :: Python :: 3.11
Classifier: Programming Language :: Python :: 3.12
Classifier: Programming Language :: Python :: 3.13
Requires-Dist: boto3 (>=1.34.63,<2.0.0)
Requires-Dist: jinja2 (>=3.1.3,<4.0.0)
Requires-Dist: kypo-python-commons (>=0.1.13,<0.2.0)
Requires-Dist: pyyaml (>=6.0.1,<7.0.0)
